toastify/__init__.py
toastify/__main__.py
toastify/lib/DesktopToast.dll
toastify/lib/notify.exe
toastify-1.1.3.dist-info/METADATA
toastify-1.1.3.dist-info/WHEEL
toastify-1.1.3.dist-info/top_level.txt
toastify-1.1.3.dist-info/RECORD
