Metadata-Version: 2.1
Name: toastify
Version: 1.1.3
Summary: Simple and Lighweight Windows 10 Toast Notifications.
Home-page: https://github.com/Tanishq-Banyal
Author: Tanishq-Banyal
Author-email: banyaltanishq@gmail.com
License: MIT
Platform: UNKNOWN
Classifier: Environment :: Win32 (MS Windows)
Classifier: Programming Language :: Python :: 3
Classifier: License :: OSI Approved :: MIT License
Classifier: Development Status :: 5 - Production/Stable
Classifier: Operating System :: Microsoft :: Windows :: Windows 10
